saltext/sap_pse/__init__.py
saltext/sap_pse/loader.py
saltext/sap_pse/version.py
saltext/sap_pse/_modules/sap_pse.py
saltext/sap_pse/_states/sap_pse.py
saltext/sap_pse/modules/sap_pse.py
saltext/sap_pse/states/sap_pse.py
saltext.sap_pse-1.0.0.dist-info/LICENSE
saltext.sap_pse-1.0.0.dist-info/METADATA
saltext.sap_pse-1.0.0.dist-info/WHEEL
saltext.sap_pse-1.0.0.dist-info/entry_points.txt
saltext.sap_pse-1.0.0.dist-info/top_level.txt
saltext.sap_pse-1.0.0.dist-info/RECORD
