Metadata-Version: 2.1
Name: saltext.sap-pse
Version: 1.0.0
Summary: SaltStack extension for SAP PSE
Home-page: https://github.com/SAPUCC/saltext-sap_pse
Author: 'Benjamin Wegener, Alexander Wilke'
License: GPLv3
Project-URL: Source, https://github.com/SAPUCC/saltext-sap_pse
Project-URL: Tracker, https://github.com/SAPUCC/saltext-sap_pse/issues
Keywords: salt-extension
Platform: any
Classifier: Programming Language :: Python
Classifier: Programming Language :: Cython
Classifier: Programming Language :: Python :: 3
Classifier: Programming Language :: Python :: 3 :: Only
Classifier: Programming Language :: Python :: 3.6
Classifier: Programming Language :: Python :: 3.7
Classifier: Programming Language :: Python :: 3.8
Classifier: Programming Language :: Python :: 3.9
Classifier: Development Status :: 4 - Beta
Classifier: Intended Audience :: Developers
Requires-Python: >=3.6
License-File: LICENSE
Requires-Dist: salt (>=3003)
Requires-Dist: PyYAML
Provides-Extra: dev
Requires-Dist: nox (==2021.6.12) ; extra == 'dev'
Requires-Dist: pre-commit (==2.13.0) ; extra == 'dev'
Requires-Dist: pylint ; extra == 'dev'
Requires-Dist: six ; extra == 'dev'
Requires-Dist: SaltPyLint ; extra == 'dev'
Provides-Extra: docs
Requires-Dist: furo ; extra == 'docs'
Requires-Dist: sphinx ; extra == 'docs'
Requires-Dist: sphinx-copybutton ; extra == 'docs'
Requires-Dist: sphinx-prompt ; extra == 'docs'
Requires-Dist: sphinxcontrib-spelling ; extra == 'docs'
Requires-Dist: importlib-metadata ; (python_version < "3.8") and extra == 'docs'
Provides-Extra: docsauto
Requires-Dist: sphinx-autobuild ; extra == 'docsauto'
Provides-Extra: tests
Requires-Dist: pytest (==6.2.4) ; extra == 'tests'
Requires-Dist: pytest-salt-factories (==0.906.0) ; extra == 'tests'
